pkg_name_validator/__init__.py
pkg_name_validator/__main__.py
pkg_name_validator-1.0.0.dist-info/LICENSE
pkg_name_validator-1.0.0.dist-info/WHEEL
pkg_name_validator-1.0.0.dist-info/METADATA
pkg_name_validator-1.0.0.dist-info/RECORD
