Metadata-Version: 2.1
Name: pkg-name-validator
Version: 1.0.0
Summary: A package for making sure your desired package name is available.
Home-page: https://github.com/tinkering-townsperson/pkg_name_validator
License: GPL-3.0-only
Author: AfterNoon PM
Author-email: h2o.Drop2010+pypi@gmail.com
Requires-Python: >=3.10,<4.0
Classifier: Intended Audience :: Developers
Classifier: License :: OSI Approved :: GNU General Public License v3 (GPLv3)
Classifier: Operating System :: OS Independent
Classifier: Programming Language :: Python :: 3
Classifier: Programming Language :: Python :: 3.10
Classifier: Programming Language :: Python :: Implementation :: CPython
Requires-Dist: requests (>=2.28.1,<3.0.0)
Project-URL: Bug Tracker, https://github.com/tinkering-townsperson/pkg_name_validator/issues
Project-URL: Repository, https://github.com/tinkering-townsperson/pkg_name_validator
